{
  "name": "Latin",
  "chart_date": "1989-07-01",
  "tracks": [
    {
      "rank": 1,
      "title": "La Incondicional",
      "artist": "Luis Miguel",
      "cover": "http://www.billboard.com/images/pref_images/q08514aqdn7.jpg",
      "spotify": "http://open.spotify.com/track/6v7Ad1gFUGZpqdvmqajchI?utm_campaign=billboard",
      "position": {
        "Last Week": "1",
        "Peak Position": 1,
        "Wks on Chart": 29
      }
    },
    {
      "rank": 2,
      "title": "BAILA MI RUMBA",
      "artist": "Jose Luis Rodriguez",
      "cover": "http://www.billboard.com/images/pref_images/p05805w4ij8.jpg",
      "position": {
        "Last Week": "2",
        "Peak Position": 1,
        "Wks on Chart": 29
      }
    },
    {
      "rank": 3,
      "title": "Este Ritmo Se Baila Asi",
      "artist": "Chayanne",
      "cover": "http://www.billboard.com/images/pref_images/p96892y6vxz.jpg",
      "spotify": "http://open.spotify.com/track/5562EZVkcwO43I03C29RuK?utm_campaign=billboard",
      "position": {
        "Last Week": "6",
        "Peak Position": 3,
        "Wks on Chart": 26
      }
    },
    {
      "rank": 4,
      "title": "Simplemente Amigos",
      "artist": "Ana Gabriel",
      "spotify": "http://open.spotify.com/track/2w3hRh03IPv1ueQ15V1XU3?utm_campaign=billboard",
      "position": {
        "Last Week": "5",
        "Peak Position": 1,
        "Wks on Chart": 29
      }
    },
    {
      "rank": 5,
      "title": "Te Amo",
      "artist": "Franco de Vita",
      "position": {
        "Last Week": "4",
        "Peak Position": 2,
        "Wks on Chart": 29
      }
    },
    {
      "rank": 6,
      "title": "AMANDOTE Y SONANDOTE",
      "artist": "Braulio",
      "position": {
        "Last Week": "3",
        "Peak Position": 3,
        "Wks on Chart": 26
      }
    },
    {
      "rank": 7,
      "title": "Como Tu",
      "artist": "Jose Jose",
      "spotify": "http://open.spotify.com/track/14oiMsexnVkJwzUgR4hlaV?utm_campaign=billboard",
      "position": {
        "Last Week": "7",
        "Peak Position": 1,
        "Wks on Chart": 25
      }
    },
    {
      "rank": 8,
      "title": "SOLO CON UN BESO",
      "artist": "Ricardo Montaner",
      "cover": "http://www.billboard.com/images/pref_images/p90134m2qzp.jpg",
      "position": {
        "Last Week": "8",
        "Peak Position": 7,
        "Wks on Chart": 33
      }
    },
    {
      "rank": 9,
      "title": "Bamboleo/Caballo Viejo",
      "artist": "Julio Iglesias",
      "cover": "http://www.billboard.com/images/pref_images/q07619dzsah.jpg",
      "position": {
        "Last Week": "12",
        "Peak Position": 6,
        "Wks on Chart": 17
      }
    },
    {
      "rank": 10,
      "title": "Amor De Noche",
      "artist": "Rocio Jurado",
      "spotify": "http://open.spotify.com/track/6ZKYHMoqS1MezkdKFjO2du?utm_campaign=billboard",
      "position": {
        "Last Week": "14",
        "Peak Position": 10,
        "Wks on Chart": 21
      }
    },
    {
      "rank": 11,
      "title": "MALA SUERTE",
      "artist": "Vikki Carr",
      "cover": "http://www.billboard.com/images/pref_images/p67030zz9la.jpg",
      "spotify": "http://open.spotify.com/track/37hTFBb4dSAwrFobS5kLNq?utm_campaign=billboard",
      "position": {
        "Last Week": "10",
        "Peak Position": 3,
        "Wks on Chart": 36
      }
    },
    {
      "rank": 12,
      "title": "QUITAME ESE HOMBRE DEL CORAZON",
      "artist": "Yolandita Monge",
      "cover": "http://www.billboard.com/images/pref_images/p75997kg0an.jpg",
      "position": {
        "Last Week": "21",
        "Peak Position": 12,
        "Wks on Chart": 11
      }
    },
    {
      "rank": 13,
      "title": "El Amor Mas Bonito",
      "artist": "Rocio Durcal",
      "cover": "http://www.billboard.com/images/pref_images/p20347m8767.jpg",
      "spotify": "http://open.spotify.com/track/6TWoJ1zQ8gmAnMifOoBYKh?utm_campaign=billboard",
      "position": {
        "Last Week": "9",
        "Peak Position": 9,
        "Wks on Chart": 26
      }
    },
    {
      "rank": 14,
      "title": "HAY OTRO EN TU LUGAR",
      "artist": "Vikki Carr",
      "cover": "http://www.billboard.com/images/pref_images/p67030zz9la.jpg",
      "spotify": "http://open.spotify.com/track/2FkWUklIbdYVdjrFWlWw9e?utm_campaign=billboard",
      "position": {
        "Last Week": "23",
        "Peak Position": 14,
        "Wks on Chart": 19
      }
    },
    {
      "rank": 15,
      "title": "Aunque mal paguen ellas",
      "artist": "Roberto Carlos/Vicente Fernandez",
      "spotify": "http://open.spotify.com/track/0k5Dw1ZT0rS8qw9e4laIlY?utm_campaign=billboard",
      "position": {
        "Last Week": "22",
        "Peak Position": 4,
        "Wks on Chart": 25
      }
    },
    {
      "rank": 16,
      "title": "VALGAME DIOS",
      "artist": "Yolanda Del Rio",
      "position": {
        "Last Week": "27",
        "Peak Position": 13,
        "Wks on Chart": 14
      }
    },
    {
      "rank": 17,
      "title": "ME FALLASTE",
      "artist": "Eddie Santiago",
      "spotify": "http://open.spotify.com/track/44LOnC2CjboZoXoL38yU32?utm_campaign=billboard",
      "position": {
        "Last Week": "17",
        "Peak Position": 16,
        "Wks on Chart": 16
      }
    },
    {
      "rank": 18,
      "title": "AMAME",
      "artist": "El Gran Combo",
      "position": {
        "Last Week": "11",
        "Peak Position": 8,
        "Wks on Chart": 14
      }
    },
    {
      "rank": 19,
      "title": "Extranandote",
      "artist": "Rocio Durcal",
      "cover": "http://www.billboard.com/images/pref_images/p20347m8767.jpg",
      "spotify": "http://open.spotify.com/track/4sAGikUHKBwoytRf3dabgj?utm_campaign=billboard",
      "position": {
        "Last Week": "24",
        "Peak Position": 8,
        "Wks on Chart": 18
      }
    },
    {
      "rank": 20,
      "title": "Asi Fue",
      "artist": "Isabel Pantoja",
      "cover": "http://www.billboard.com/images/pref_images/p20788nklj3.jpg",
      "spotify": "http://open.spotify.com/track/3NTVrovdayzDPiu2lpgnPY?utm_campaign=billboard",
      "position": {
        "Last Week": "19",
        "Peak Position": 2,
        "Wks on Chart": 33
      }
    },
    {
      "rank": 21,
      "title": "El Gran Baron",
      "artist": "Willie Colon",
      "cover": "http://www.billboard.com/images/pref_images/p04740a5qx7.jpg",
      "position": {
        "Last Week": "20",
        "Peak Position": 13,
        "Wks on Chart": 11
      }
    },
    {
      "rank": 22,
      "title": "Quisiera",
      "artist": "Emmanuel",
      "cover": "http://www.billboard.com/images/pref_images/q03507ezqvp.jpg",
      "position": {
        "Last Week": "--",
        "Peak Position": 7,
        "Wks on Chart": 20
      }
    },
    {
      "rank": 23,
      "title": "CORAZON EN BLANCO",
      "artist": "Lourdes Robles",
      "position": {
        "Last Week": "--",
        "Peak Position": 15,
        "Wks on Chart": 10
      }
    },
    {
      "rank": 24,
      "title": "LA NEGRA TOMASA",
      "artist": "Caifanes",
      "position": {
        "Last Week": "29",
        "Peak Position": 24,
        "Wks on Chart": 7
      }
    },
    {
      "rank": 25,
      "title": "AMOR QUE NACE",
      "artist": "Los Caminantes",
      "spotify": "http://open.spotify.com/track/42BxwtlqeRAG64QEocjET1?utm_campaign=billboard",
      "position": {
        "Last Week": "40",
        "Peak Position": 22,
        "Wks on Chart": 15
      }
    },
    {
      "rank": 26,
      "title": "Lo Que Las Mujeres Callamos",
      "artist": "Daniela Romo",
      "spotify": "http://open.spotify.com/track/6rsuX0nwqepanGGJMI3brJ?utm_campaign=billboard",
      "position": {
        "Last Week": "--",
        "Peak Position": 26,
        "Wks on Chart": 10
      }
    },
    {
      "rank": 27,
      "title": "Y Voy Hacer Feliz",
      "artist": "Marisela",
      "cover": "http://www.billboard.com/images/pref_images/p20786uil96.jpg",
      "position": {
        "Last Week": "--",
        "Peak Position": 6,
        "Wks on Chart": 24
      }
    },
    {
      "rank": 28,
      "title": "Ya No Puedo Volver Contigo",
      "artist": "Marisela",
      "cover": "http://www.billboard.com/images/pref_images/p20786uil96.jpg",
      "spotify": "http://open.spotify.com/track/1Slq1qSNTvuM62HZaGfaG0?utm_campaign=billboard",
      "position": {
        "Last Week": "13",
        "Peak Position": 5,
        "Wks on Chart": 17
      }
    },
    {
      "rank": 29,
      "title": "Vete Con Ella",
      "artist": "Lucerito",
      "position": {
        "Last Week": "31",
        "Peak Position": 7,
        "Wks on Chart": 17
      }
    },
    {
      "rank": 30,
      "title": "Aventurero",
      "artist": "Lucia Mendez",
      "cover": "http://www.billboard.com/images/pref_images/p98651l6gti.jpg",
      "spotify": "http://open.spotify.com/track/6xfFsCevJdtTqU9uTHEfRt?utm_campaign=billboard",
      "position": {
        "Last Week": "26",
        "Peak Position": 22,
        "Wks on Chart": 9
      }
    },
    {
      "rank": 31,
      "title": "Piel De Azucar",
      "artist": "Jose Jose",
      "position": {
        "Last Week": "18",
        "Peak Position": 16,
        "Wks on Chart": 33
      }
    },
    {
      "rank": 32,
      "title": "PERDON POR TUS LAGRIMAS",
      "artist": "Los Yonic s",
      "position": {
        "Last Week": "39",
        "Peak Position": 20,
        "Wks on Chart": 17
      }
    },
    {
      "rank": 33,
      "title": "No Podras Escapar De Mi",
      "artist": "Willie Gonzalez",
      "spotify": "http://open.spotify.com/track/0lacKf3kZXbQ1F17QvurMs?utm_campaign=billboard",
      "position": {
        "Last Week": "15",
        "Peak Position": 15,
        "Wks on Chart": 12
      }
    },
    {
      "rank": 34,
      "title": "Mi Complice",
      "artist": "Tommy Olivencia",
      "position": {
        "Last Week": "34",
        "Peak Position": 24,
        "Wks on Chart": 8
      }
    },
    {
      "rank": 35,
      "title": "AMOR DE POCO TIEMPO",
      "artist": "Tony Vega",
      "cover": "http://www.billboard.com/images/pref_images/p17147gbw3j.jpg",
      "spotify": "http://open.spotify.com/track/70f0bG4pq5xYxPk30BXuji?utm_campaign=billboard",
      "position": {
        "Last Week": "--",
        "Peak Position": 24,
        "Wks on Chart": 4
      }
    },
    {
      "rank": 36,
      "title": "Mi Corazon Tiene Mente Propia",
      "artist": "Ednita Nazario",
      "position": {
        "Last Week": "25",
        "Peak Position": 25,
        "Wks on Chart": 5
      }
    },
    {
      "rank": 37,
      "title": "Aguacero",
      "artist": "El Gran Combo",
      "position": {
        "Last Week": "--",
        "Peak Position": 12,
        "Wks on Chart": 12
      }
    },
    {
      "rank": 38,
      "title": "Tan Enamorados",
      "artist": "Ricardo Montaner",
      "cover": "http://www.billboard.com/images/pref_images/p90134m2qzp.jpg",
      "spotify": "http://open.spotify.com/track/3UNYKYeae85XQARKgkJENn?utm_campaign=billboard",
      "position": {
        "Last Week": "37",
        "Peak Position": 9,
        "Wks on Chart": 40
      }
    },
    {
      "rank": 39,
      "title": "Tristes Momentos",
      "artist": "Roberto Carlos",
      "cover": "http://www.billboard.com/images/pref_images/q03510xklug.jpg",
      "position": {
        "Last Week": "36",
        "Peak Position": 11,
        "Wks on Chart": 20
      }
    },
    {
      "rank": 40,
      "title": "Que Hablen",
      "artist": "Jose Javier Solis",
      "position": {
        "Last Week": "35",
        "Peak Position": 35,
        "Wks on Chart": 3
      }
    }
  ]
}