{
  "name": "Latin",
  "chart_date": "2022-04-16",
  "tracks": [
    {
      "rank": 1,
      "title": "MAMIII",
      "artist": "Becky G X Karol G",
      "position": {
        "Last Week": "2",
        "Peak Position": 1,
        "Wks on Chart": 8
      }
    },
    {
      "rank": 2,
      "title": "Soy El Unico",
      "artist": "Yahritza y Su Esencia",
      "position": {
        "Last Week": "1",
        "Peak Position": 1,
        "Wks on Chart": 2
      }
    },
    {
      "rank": 3,
      "title": "Pepas",
      "artist": "Farruko",
      "position": {
        "Last Week": "3",
        "Peak Position": 1,
        "Wks on Chart": 40
      }
    },
    {
      "rank": 4,
      "title": "Envolver",
      "artist": "Anitta",
      "position": {
        "Last Week": "6",
        "Peak Position": 4,
        "Wks on Chart": 5
      }
    },
    {
      "rank": 5,
      "title": "Dakiti",
      "artist": "Bad Bunny & Jhay Cortez",
      "position": {
        "Last Week": "4",
        "Peak Position": 1,
        "Wks on Chart": 75
      }
    },
    {
      "rank": 6,
      "title": "Yonaguni",
      "artist": "Bad Bunny",
      "position": {
        "Last Week": "9",
        "Peak Position": 1,
        "Wks on Chart": 44
      }
    },
    {
      "rank": 7,
      "title": "Desesperados",
      "artist": "Rauw Alejandro & Chencho Corleone",
      "position": {
        "Last Week": "10",
        "Peak Position": 5,
        "Wks on Chart": 17
      }
    },
    {
      "rank": 8,
      "title": "X Ultima Vez",
      "artist": "Daddy Yankee & Bad Bunny",
      "position": {
        "Last Week": "5",
        "Peak Position": 5,
        "Wks on Chart": 2
      }
    },
    {
      "rank": 9,
      "title": "Sigue",
      "artist": "J Balvin & Ed Sheeran",
      "position": {
        "Last Week": "7",
        "Peak Position": 7,
        "Wks on Chart": 2
      }
    },
    {
      "rank": 10,
      "title": "Chale!",
      "artist": "Eden Munoz",
      "position": {
        "Last Week": "14",
        "Peak Position": 10,
        "Wks on Chart": 6
      }
    },
    {
      "rank": 11,
      "title": "Forever My Love",
      "artist": "J Balvin & Ed Sheeran",
      "position": {
        "Last Week": "11",
        "Peak Position": 11,
        "Wks on Chart": 2
      }
    },
    {
      "rank": 12,
      "title": "Si Tu Me Busca",
      "artist": "Anuel AA & Yailin La Mas Viral",
      "position": {
        "Last Week": "-",
        "Peak Position": 12,
        "Wks on Chart": 1
      }
    },
    {
      "rank": 13,
      "title": "Dos Oruguitas",
      "artist": "Sebastian Yatra",
      "position": {
        "Last Week": "8",
        "Peak Position": 2,
        "Wks on Chart": 15
      }
    },
    {
      "rank": 14,
      "title": "Sus Huellas",
      "artist": "Romeo Santos",
      "position": {
        "Last Week": "15",
        "Peak Position": 10,
        "Wks on Chart": 8
      }
    },
    {
      "rank": 15,
      "title": "Ya No Somos Ni Seremos",
      "artist": "Christian Nodal",
      "position": {
        "Last Week": "17",
        "Peak Position": 8,
        "Wks on Chart": 7
      }
    },
    {
      "rank": 16,
      "title": "Si Te Pudiera Mentir",
      "artist": "Calibre 50",
      "position": {
        "Last Week": "16",
        "Peak Position": 8,
        "Wks on Chart": 24
      }
    },
    {
      "rank": 17,
      "title": "Remix",
      "artist": "Daddy Yankee",
      "position": {
        "Last Week": "13",
        "Peak Position": 13,
        "Wks on Chart": 2
      }
    },
    {
      "rank": 18,
      "title": "Fumando Mota",
      "artist": "Los Lara",
      "position": {
        "Last Week": "18",
        "Peak Position": 10,
        "Wks on Chart": 13
      }
    },
    {
      "rank": 19,
      "title": "Medallo",
      "artist": "Blessd, Justin Quiles & Lenny Tavarez",
      "position": {
        "Last Week": "26",
        "Peak Position": 19,
        "Wks on Chart": 14
      }
    },
    {
      "rank": 20,
      "title": "Colombia, Mi Encanto",
      "artist": "Carlos Vives",
      "position": {
        "Last Week": "20",
        "Peak Position": 6,
        "Wks on Chart": 15
      }
    },
    {
      "rank": 21,
      "title": "No Le Aflojo",
      "artist": "Los Gemelos de Sinaloa X Fuerza Regida",
      "position": {
        "Last Week": "31",
        "Peak Position": 21,
        "Wks on Chart": 5
      }
    },
    {
      "rank": 22,
      "title": "Cada Quien",
      "artist": "Grupo Firme & Maluma",
      "position": {
        "Last Week": "27",
        "Peak Position": 7,
        "Wks on Chart": 18
      }
    },
    {
      "rank": 23,
      "title": "Andamos Mejor",
      "artist": "Los Gemelos de Sinaloa",
      "position": {
        "Last Week": "29",
        "Peak Position": 23,
        "Wks on Chart": 7
      }
    },
    {
      "rank": 24,
      "title": "Ojos Rojos",
      "artist": "Nicky Jam",
      "position": {
        "Last Week": "35",
        "Peak Position": 24,
        "Wks on Chart": 10
      }
    },
    {
      "rank": 25,
      "title": "Sensual Bebe",
      "artist": "Jhay Cortez",
      "position": {
        "Last Week": "34",
        "Peak Position": 20,
        "Wks on Chart": 4
      }
    },
    {
      "rank": 26,
      "title": "Tacones Rojos",
      "artist": "Sebastian Yatra",
      "position": {
        "Last Week": "25",
        "Peak Position": 12,
        "Wks on Chart": 18
      }
    },
    {
      "rank": 27,
      "title": "!WOW BB!",
      "artist": "Natti Natasha, Chimbala & El Alfa",
      "position": {
        "Last Week": "43",
        "Peak Position": 27,
        "Wks on Chart": 6
      }
    },
    {
      "rank": 28,
      "title": "Una Noche En Medellin",
      "artist": "Cris Mj",
      "position": {
        "Last Week": "40",
        "Peak Position": 28,
        "Wks on Chart": 3
      }
    },
    {
      "rank": 29,
      "title": "Si Me Ven",
      "artist": "Los Gemelos de Sinaloa",
      "position": {
        "Last Week": "41",
        "Peak Position": 29,
        "Wks on Chart": 8
      }
    },
    {
      "rank": 30,
      "title": "Ojos Cerrados",
      "artist": "Banda MS Featuring Carin Leon",
      "position": {
        "Last Week": "36",
        "Peak Position": 18,
        "Wks on Chart": 13
      }
    },
    {
      "rank": 31,
      "title": "Ahi Donde Me Ven",
      "artist": "Angela Aguilar",
      "position": {
        "Last Week": "-",
        "Peak Position": 31,
        "Wks on Chart": 2
      }
    },
    {
      "rank": 32,
      "title": "Me Acostumbre A Lo Bueno",
      "artist": "Fuerza Regida",
      "position": {
        "Last Week": "46",
        "Peak Position": 24,
        "Wks on Chart": 13
      }
    },
    {
      "rank": 33,
      "title": "Mujeriego",
      "artist": "Ryan Castro",
      "position": {
        "Last Week": "48",
        "Peak Position": 33,
        "Wks on Chart": 10
      }
    },
    {
      "rank": 34,
      "title": "Y Si Se Quiere Ir",
      "artist": "Luis Angel \"El Flaco\"",
      "position": {
        "Last Week": "47",
        "Peak Position": 34,
        "Wks on Chart": 6
      }
    },
    {
      "rank": 35,
      "title": "Subelo",
      "artist": "Anuel AA, Myke Towers & Jhay Cortez",
      "position": {
        "Last Week": "44",
        "Peak Position": 12,
        "Wks on Chart": 20
      }
    },
    {
      "rank": 36,
      "title": "No",
      "artist": "Alfredo Olivas",
      "position": {
        "Last Week": "49",
        "Peak Position": 36,
        "Wks on Chart": 3
      }
    },
    {
      "rank": 37,
      "title": "Te Espero",
      "artist": "Prince Royce & Maria Becerra",
      "position": {
        "Last Week": "-",
        "Peak Position": 37,
        "Wks on Chart": 4
      }
    },
    {
      "rank": 38,
      "title": "Fuera de Servicio",
      "artist": "El Fantasma",
      "position": {
        "Last Week": "-",
        "Peak Position": 38,
        "Wks on Chart": 1
      }
    },
    {
      "rank": 39,
      "title": "Borracho",
      "artist": "Sech & DJ Khaled",
      "position": {
        "Last Week": "50",
        "Peak Position": 28,
        "Wks on Chart": 19
      }
    },
    {
      "rank": 40,
      "title": "Fuera del Mercado",
      "artist": "Danny Ocean",
      "position": {
        "Last Week": "-",
        "Peak Position": 40,
        "Wks on Chart": 1
      }
    },
    {
      "rank": 41,
      "title": "Los Botones Azules",
      "artist": "Junior H & Luis R Conriquez",
      "position": {
        "Last Week": "-",
        "Peak Position": 41,
        "Wks on Chart": 1
      }
    },
    {
      "rank": 42,
      "title": "Hot",
      "artist": "Daddy Yankee & Pitbull",
      "position": {
        "Last Week": "23",
        "Peak Position": 23,
        "Wks on Chart": 2
      }
    },
    {
      "rank": 43,
      "title": "Plan A",
      "artist": "Paulo Londra",
      "position": {
        "Last Week": "-",
        "Peak Position": 43,
        "Wks on Chart": 1
      }
    },
    {
      "rank": 44,
      "title": "Hibrido",
      "artist": "Virlan Garcia",
      "position": {
        "Last Week": "-",
        "Peak Position": 44,
        "Wks on Chart": 1
      }
    },
    {
      "rank": 45,
      "title": "Deprimida",
      "artist": "Ozuna",
      "position": {
        "Last Week": "-",
        "Peak Position": 34,
        "Wks on Chart": 5
      }
    },
    {
      "rank": 46,
      "title": "Los Mire Con Talento",
      "artist": "Fuerza Regida X Luis R Conriquez X Calle 24",
      "position": {
        "Last Week": "-",
        "Peak Position": 24,
        "Wks on Chart": 17
      }
    },
    {
      "rank": 47,
      "title": "Rumbaton",
      "artist": "Daddy Yankee",
      "position": {
        "Last Week": "19",
        "Peak Position": 19,
        "Wks on Chart": 2
      }
    },
    {
      "rank": 48,
      "title": "Nada de Nada",
      "artist": "Marc Anthony",
      "position": {
        "Last Week": "-",
        "Peak Position": 37,
        "Wks on Chart": 2
      }
    },
    {
      "rank": 49,
      "title": "2010",
      "artist": "Mora",
      "position": {
        "Last Week": "-",
        "Peak Position": 49,
        "Wks on Chart": 1
      }
    },
    {
      "rank": 50,
      "title": "Me Vale Perderte",
      "artist": "Banda Rancho Viejo de Julio Aramburo La Bandononon Desde El Ion de Los Peraza",
      "position": {
        "Last Week": "-",
        "Peak Position": 50,
        "Wks on Chart": 1
      }
    }
  ]
}