{
  "name": "Hip-Hop",
  "chart_date": "2001-12-01",
  "tracks": [
    {
      "rank": 1,
      "title": "U Got It Bad",
      "artist": "Usher",
      "cover": "http://www.billboard.com/images/pref_images/p99056mvv4y.jpg",
      "spotify": "http://open.spotify.com/track/7J41dYQolQJEtj3UmKLu5r?utm_campaign=billboard",
      "position": {
        "Last Week": "1",
        "Peak Position": 1,
        "Wks on Chart": 13
      }
    },
    {
      "rank": 2,
      "title": "Rock The Boat",
      "artist": "Aaliyah",
      "cover": "http://www.billboard.com/images/pref_images/p17228chqhg.jpg",
      "spotify": "http://open.spotify.com/track/3Q6qrj7HIgu9fxhHBkfmdi?utm_campaign=billboard",
      "position": {
        "Last Week": "2",
        "Peak Position": 2,
        "Wks on Chart": 17
      }
    },
    {
      "rank": 3,
      "title": "Differences",
      "artist": "Ginuwine",
      "cover": "http://www.billboard.com/images/pref_images/q03213kvxfo.jpg",
      "spotify": "http://open.spotify.com/track/0O5b1927V6FbLsZRtf7idi?utm_campaign=billboard",
      "position": {
        "Last Week": "3",
        "Peak Position": 1,
        "Wks on Chart": 23
      }
    },
    {
      "rank": 4,
      "title": "Girls, Girls, Girls",
      "artist": "Jay-Z",
      "cover": "http://www.billboard.com/images/pref_images/q09318sff3b.jpg",
      "spotify": "http://open.spotify.com/track/0vzb8Ii9B2fP9c0POFGPOZ?utm_campaign=billboard",
      "position": {
        "Last Week": "5",
        "Peak Position": 4,
        "Wks on Chart": 10
      }
    },
    {
      "rank": 5,
      "title": "Family Affair",
      "artist": "Mary J. Blige",
      "cover": "http://www.billboard.com/images/pref_images/q24347ishmq.jpg",
      "spotify": "http://open.spotify.com/track/31ZmrkzUIg0BOoPdZezNiB?utm_campaign=billboard",
      "position": {
        "Last Week": "4",
        "Peak Position": 1,
        "Wks on Chart": 20
      }
    },
    {
      "rank": 6,
      "title": "Lifetime",
      "artist": "Maxwell",
      "cover": "http://www.billboard.com/images/pref_images/p70699oo2fd.jpg",
      "spotify": "http://open.spotify.com/track/0tXq1ob3ysGZN2oK1abtyp?utm_campaign=billboard",
      "position": {
        "Last Week": "6",
        "Peak Position": 5,
        "Wks on Chart": 20
      }
    },
    {
      "rank": 7,
      "title": "Livin' It Up",
      "artist": "Ja Rule Featuring Case",
      "cover": "http://www.billboard.com/images/pref_images/p56481wjlv7.jpg",
      "spotify": "http://open.spotify.com/track/0UZ5D7IZkiR3ZUYl6AK0do?utm_campaign=billboard",
      "position": {
        "Last Week": "7",
        "Peak Position": 4,
        "Wks on Chart": 17
      }
    },
    {
      "rank": 8,
      "title": "You Gets No Love",
      "artist": "Faith Evans",
      "cover": "http://www.billboard.com/images/pref_images/p73114pu06f.jpg",
      "spotify": "http://open.spotify.com/track/61kG6g3btiapbSVEj3D0Hb?utm_campaign=billboard",
      "position": {
        "Last Week": "8",
        "Peak Position": 8,
        "Wks on Chart": 13
      }
    },
    {
      "rank": 9,
      "title": "Always On Time",
      "artist": "Ja Rule Featuring Ashanti",
      "cover": "http://www.billboard.com/images/pref_images/p56481wjlv7.jpg",
      "spotify": "http://open.spotify.com/track/4YA7nxDtAVE2R1Eryx7uRu?utm_campaign=billboard",
      "position": {
        "Last Week": "15",
        "Peak Position": 1,
        "Wks on Chart": 5
      }
    },
    {
      "rank": 10,
      "title": "We Thuggin'",
      "artist": "Fat Joe Featuring R. Kelly",
      "cover": "http://www.billboard.com/images/pref_images/p68299ddp0v.jpg",
      "spotify": "http://open.spotify.com/track/2EcW94ak7kYH4mDMvI7iWg?utm_campaign=billboard",
      "position": {
        "Last Week": "13",
        "Peak Position": 5,
        "Wks on Chart": 11
      }
    },
    {
      "rank": 11,
      "title": "Butterflies",
      "artist": "Michael Jackson",
      "cover": "http://www.billboard.com/images/pref_images/q10408h1mg5.jpg",
      "spotify": "http://open.spotify.com/track/0zDBwxZMpxwRuhUUk4f5ne?utm_campaign=billboard",
      "position": {
        "Last Week": "14",
        "Peak Position": 2,
        "Wks on Chart": 5
      }
    },
    {
      "rank": 12,
      "title": "Caramel",
      "artist": "City High Featuring Eve",
      "cover": "http://www.billboard.com/images/pref_images/p2424512u80.jpg",
      "spotify": "http://open.spotify.com/track/5dXmPzPDTMWmxmpzxAV1JZ?utm_campaign=billboard",
      "position": {
        "Last Week": "9",
        "Peak Position": 9,
        "Wks on Chart": 11
      }
    },
    {
      "rank": 13,
      "title": "A Woman's Worth",
      "artist": "Alicia Keys",
      "cover": "http://www.billboard.com/images/pref_images/q02930nk8fk.jpg",
      "spotify": "http://open.spotify.com/track/1NRorokmYEtr1koWybvaE4?utm_campaign=billboard",
      "position": {
        "Last Week": "11",
        "Peak Position": 3,
        "Wks on Chart": 8
      }
    },
    {
      "rank": 14,
      "title": "Lights, Camera, Action!",
      "artist": "Mr. Cheeks",
      "cover": "http://www.billboard.com/images/pref_images/p75532nk4y3.jpg",
      "spotify": "http://open.spotify.com/track/0MVMYjIk1N3nO8omHZRaOd?utm_campaign=billboard",
      "position": {
        "Last Week": "17",
        "Peak Position": 1,
        "Wks on Chart": 15
      }
    },
    {
      "rank": 15,
      "title": "Raise Up",
      "artist": "Petey Pablo",
      "cover": "http://www.billboard.com/images/pref_images/p57078olt04.jpg",
      "spotify": "http://open.spotify.com/track/02GwPAncasVL82yC7y2hmN?utm_campaign=billboard",
      "position": {
        "Last Week": "10",
        "Peak Position": 9,
        "Wks on Chart": 24
      }
    },
    {
      "rank": 16,
      "title": "Who We Be",
      "artist": "DMX",
      "cover": "http://www.billboard.com/images/pref_images/p97232ywr1j.jpg",
      "spotify": "http://open.spotify.com/track/5v1SSuJCyPHJv9ylVK3LBL?utm_campaign=billboard",
      "position": {
        "Last Week": "16",
        "Peak Position": 16,
        "Wks on Chart": 12
      }
    },
    {
      "rank": 17,
      "title": "Love Of My Life",
      "artist": "Brian McKnight",
      "cover": "http://www.billboard.com/images/pref_images/q07608oo1th.jpg",
      "spotify": "http://open.spotify.com/track/3wzTG2nwvZOaJujWGNaOGa?utm_campaign=billboard",
      "position": {
        "Last Week": "18",
        "Peak Position": 11,
        "Wks on Chart": 19
      }
    },
    {
      "rank": 18,
      "title": "Goodbye",
      "artist": "Jagged Edge",
      "cover": "http://www.billboard.com/images/pref_images/q25306csl27.jpg",
      "spotify": "http://open.spotify.com/track/3PcocqQL1Qn6LtUxjSlk4R?utm_campaign=billboard",
      "position": {
        "Last Week": "19",
        "Peak Position": 18,
        "Wks on Chart": 10
      }
    },
    {
      "rank": 19,
      "title": "Ugly",
      "artist": "Bubba Sparxxx",
      "cover": "http://www.billboard.com/images/pref_images/q06143j0q80.jpg",
      "spotify": "http://open.spotify.com/track/3NOq1Gpiy4KwDni8NhOmHQ?utm_campaign=billboard",
      "position": {
        "Last Week": "12",
        "Peak Position": 6,
        "Wks on Chart": 15
      }
    },
    {
      "rank": 20,
      "title": "Roll Out (My Business)",
      "artist": "Ludacris",
      "cover": "http://www.billboard.com/images/pref_images/p73615ac4sb.jpg",
      "position": {
        "Last Week": "23",
        "Peak Position": 7,
        "Wks on Chart": 6
      }
    },
    {
      "rank": 21,
      "title": "#1",
      "artist": "Nelly",
      "cover": "http://www.billboard.com/images/pref_images/q09622kdgbh.jpg",
      "spotify": "http://open.spotify.com/track/7rSj5gEdN5KgHwbnEVAZ4b?utm_campaign=billboard",
      "position": {
        "Last Week": "20",
        "Peak Position": 20,
        "Wks on Chart": 12
      }
    },
    {
      "rank": 22,
      "title": "Brotha",
      "artist": "Angie Stone",
      "cover": "http://www.billboard.com/images/pref_images/p75517nu334.jpg",
      "spotify": "http://open.spotify.com/track/2sNAjuCXxyj8jHt93t9IJ9?utm_campaign=billboard",
      "position": {
        "Last Week": "27",
        "Peak Position": 13,
        "Wks on Chart": 10
      }
    },
    {
      "rank": 23,
      "title": "You Rock My World",
      "artist": "Michael Jackson",
      "cover": "http://www.billboard.com/images/pref_images/q10408h1mg5.jpg",
      "spotify": "http://open.spotify.com/track/1XDtOKKCOGcBKtDlzjBkks?utm_campaign=billboard",
      "position": {
        "Last Week": "22",
        "Peak Position": 13,
        "Wks on Chart": 13
      }
    },
    {
      "rank": 24,
      "title": "Diddy",
      "artist": "P. Diddy Featuring The Neptunes",
      "spotify": "http://open.spotify.com/track/6EtkH6EfTfNLjUHKDylEym?utm_campaign=billboard",
      "position": {
        "Last Week": "21",
        "Peak Position": 21,
        "Wks on Chart": 10
      }
    },
    {
      "rank": 25,
      "title": "Gone",
      "artist": "'N Sync",
      "cover": "http://www.billboard.com/images/pref_images/p23988bg9ta.jpg",
      "spotify": "http://open.spotify.com/track/2yuGSFSzPeJziqGxUPrvad?utm_campaign=billboard",
      "position": {
        "Last Week": "36",
        "Peak Position": 14,
        "Wks on Chart": 4
      }
    },
    {
      "rank": 26,
      "title": "Take Away",
      "artist": "Missy \"Misdemeanor\" Elliott Featuring Ginuwine & Introducing Tweet",
      "position": {
        "Last Week": "34",
        "Peak Position": 25,
        "Wks on Chart": 5
      }
    },
    {
      "rank": 27,
      "title": "Break Ya Neck",
      "artist": "Busta Rhymes",
      "cover": "http://www.billboard.com/images/pref_images/p70920kv04c.jpg",
      "spotify": "http://open.spotify.com/track/0svl7cK07gK1ia5ainczU5?utm_campaign=billboard",
      "position": {
        "Last Week": "30",
        "Peak Position": 10,
        "Wks on Chart": 8
      }
    },
    {
      "rank": 28,
      "title": "Can't Deny It",
      "artist": "Fabolous Featuring Nate Dogg",
      "cover": "http://www.billboard.com/images/pref_images/p74555fk1du.jpg",
      "spotify": "http://open.spotify.com/track/7K4Aq4awgYvDKEJdEvvl4j?utm_campaign=billboard",
      "position": {
        "Last Week": "24",
        "Peak Position": 13,
        "Wks on Chart": 24
      }
    },
    {
      "rank": 29,
      "title": "I'm Real",
      "artist": "Jennifer Lopez Featuring Ja Rule",
      "cover": "http://www.billboard.com/images/pref_images/p76527yw3p8.jpg",
      "spotify": "http://open.spotify.com/track/1gaUODQzPR6eNcJtNe0cyZ?utm_campaign=billboard",
      "position": {
        "Last Week": "25",
        "Peak Position": 2,
        "Wks on Chart": 24
      }
    },
    {
      "rank": 30,
      "title": "Where The Party At",
      "artist": "Jagged Edge With Nelly",
      "spotify": "http://open.spotify.com/track/5mNV8Mz59bzyuQ53gTw0c0?utm_campaign=billboard",
      "position": {
        "Last Week": "26",
        "Peak Position": 1,
        "Wks on Chart": 29
      }
    },
    {
      "rank": 31,
      "title": "Emotion",
      "artist": "Destiny's Child",
      "cover": "http://www.billboard.com/images/pref_images/q07279l1ucp.jpg",
      "spotify": "http://open.spotify.com/track/7E6e5lZPJ5BgahnsJanAsP?utm_campaign=billboard",
      "position": {
        "Last Week": "28",
        "Peak Position": 28,
        "Wks on Chart": 10
      }
    },
    {
      "rank": 32,
      "title": "Son Of A Gun",
      "artist": "Janet Featuring Missy Elliott, P. Diddy & Carly Simon",
      "spotify": "http://open.spotify.com/track/7iBjvDLhfBrXxsVEUjENOu?utm_campaign=billboard",
      "position": {
        "Last Week": "35",
        "Peak Position": 26,
        "Wks on Chart": 5
      }
    },
    {
      "rank": 33,
      "title": "Let's Stay Home Tonight",
      "artist": "Joe",
      "cover": "http://www.billboard.com/images/pref_images/p83683b8e0j.jpg",
      "spotify": "http://open.spotify.com/track/7umwyk9FNWoLUZsw7B9OII?utm_campaign=billboard",
      "position": {
        "Last Week": "46",
        "Peak Position": 18,
        "Wks on Chart": 4
      }
    },
    {
      "rank": 34,
      "title": "Dance With Me",
      "artist": "112",
      "cover": "http://www.billboard.com/images/pref_images/p56495xzkhl.jpg",
      "spotify": "http://open.spotify.com/track/06EmqZJolHpHSwNKLHVmqB?utm_campaign=billboard",
      "position": {
        "Last Week": "32",
        "Peak Position": 20,
        "Wks on Chart": 22
      }
    },
    {
      "rank": 35,
      "title": "What Am I Gonna Do",
      "artist": "Tyrese",
      "cover": "http://www.billboard.com/images/pref_images/p82680inyrb.jpg",
      "spotify": "http://open.spotify.com/track/7FFQsnjzumC6eyCXRFPQ2f?utm_campaign=billboard",
      "position": {
        "Last Week": "29",
        "Peak Position": 24,
        "Wks on Chart": 16
      }
    },
    {
      "rank": 36,
      "title": "What If",
      "artist": "Babyface",
      "cover": "http://www.billboard.com/images/pref_images/q13523cg5zq.jpg",
      "spotify": "http://open.spotify.com/track/4AFhkn04YASMuvUxVMJKmW?utm_campaign=billboard",
      "position": {
        "Last Week": "33",
        "Peak Position": 28,
        "Wks on Chart": 15
      }
    },
    {
      "rank": 37,
      "title": "From Her Mama (Mama Got A**)",
      "artist": "Juvenile",
      "cover": "http://www.billboard.com/images/pref_images/q26491pjvg3.jpg",
      "position": {
        "Last Week": "41",
        "Peak Position": 27,
        "Wks on Chart": 7
      }
    },
    {
      "rank": 38,
      "title": "Feelin' On Yo Booty",
      "artist": "R. Kelly",
      "cover": "http://www.billboard.com/images/pref_images/p97712tbynu.jpg",
      "spotify": "http://open.spotify.com/track/61GnkRbJynRPbwIjFvnVZE?utm_campaign=billboard",
      "position": {
        "Last Week": "31",
        "Peak Position": 9,
        "Wks on Chart": 38
      }
    },
    {
      "rank": 39,
      "title": "Bad Intentions",
      "artist": "Dr. Dre Featuring Knoc-Turn'Al",
      "cover": "http://www.billboard.com/images/pref_images/q08624qr4l0.jpg",
      "spotify": "http://open.spotify.com/track/3e9KHYgTDIbVTez3IFZZl2?utm_campaign=billboard",
      "position": {
        "Last Week": "39",
        "Peak Position": 33,
        "Wks on Chart": 7
      }
    },
    {
      "rank": 40,
      "title": "Fatty Girl",
      "artist": "Ludacris, LL Cool J & Keith Murray",
      "position": {
        "Last Week": "40",
        "Peak Position": 32,
        "Wks on Chart": 10
      }
    },
    {
      "rank": 41,
      "title": "Just In Case",
      "artist": "Jaheim",
      "cover": "http://www.billboard.com/images/pref_images/q11185bj28a.jpg",
      "spotify": "http://open.spotify.com/track/6VC6nUEHorjCm6XBXIiCES?utm_campaign=billboard",
      "position": {
        "Last Week": "38",
        "Peak Position": 15,
        "Wks on Chart": 30
      }
    },
    {
      "rank": 42,
      "title": "Nothing In This World",
      "artist": "Keke Wyatt Featuring Avant",
      "cover": "http://www.billboard.com/images/pref_images/p78288r8vqj.jpg",
      "position": {
        "Last Week": "49",
        "Peak Position": 4,
        "Wks on Chart": 8
      }
    },
    {
      "rank": 43,
      "title": "The Wash",
      "artist": "Dr. Dre & Snoop Dogg",
      "position": {
        "Last Week": "43",
        "Peak Position": 43,
        "Wks on Chart": 5
      }
    },
    {
      "rank": 44,
      "title": "No More Drama",
      "artist": "Mary J. Blige",
      "cover": "http://www.billboard.com/images/pref_images/q24347ishmq.jpg",
      "spotify": "http://open.spotify.com/track/7nWsh14AHpnTzq1Xejz90U?utm_campaign=billboard",
      "position": {
        "Last Week": "47",
        "Peak Position": 16,
        "Wks on Chart": 11
      }
    },
    {
      "rank": 45,
      "title": "Fallin'",
      "artist": "Alicia Keys",
      "cover": "http://www.billboard.com/images/pref_images/q02930nk8fk.jpg",
      "spotify": "http://open.spotify.com/track/3unsLiH5FXmaDWtT5Imolu?utm_campaign=billboard",
      "position": {
        "Last Week": "44",
        "Peak Position": 1,
        "Wks on Chart": 31
      }
    },
    {
      "rank": 46,
      "title": "I'm A Thug",
      "artist": "Trick Daddy",
      "spotify": "http://open.spotify.com/track/6j2aNuhJJUnRj6UHcvn5PI?utm_campaign=billboard",
      "position": {
        "Last Week": "45",
        "Peak Position": 8,
        "Wks on Chart": 23
      }
    },
    {
      "rank": 47,
      "title": "Izzo (H.O.V.A.)",
      "artist": "Jay-Z",
      "cover": "http://www.billboard.com/images/pref_images/q09318sff3b.jpg",
      "spotify": "http://open.spotify.com/track/16rzBmxDZY8ZGGK2lWTPtf?utm_campaign=billboard",
      "position": {
        "Last Week": "37",
        "Peak Position": 4,
        "Wks on Chart": 20
      }
    },
    {
      "rank": 48,
      "title": "Made To Love Ya",
      "artist": "Gerald Levert",
      "cover": "http://www.billboard.com/images/pref_images/q00576o7q2q.jpg",
      "spotify": "http://open.spotify.com/track/0hU05v2mRmgiYATHNcTH3h?utm_campaign=billboard",
      "position": {
        "Last Week": "48",
        "Peak Position": 37,
        "Wks on Chart": 17
      }
    },
    {
      "rank": 49,
      "title": "Don't You Forget It",
      "artist": "Glenn Lewis",
      "cover": "http://www.billboard.com/images/pref_images/p2525366i1l.jpg",
      "spotify": "http://open.spotify.com/track/7vKYuqKAySUizIkcAl4Oal?utm_campaign=billboard",
      "position": {
        "Last Week": "57",
        "Peak Position": 10,
        "Wks on Chart": 6
      }
    },
    {
      "rank": 50,
      "title": "The Way",
      "artist": "Jill Scott",
      "cover": "http://www.billboard.com/images/pref_images/q00272j1o65.jpg",
      "spotify": "http://open.spotify.com/track/49aUxrufliNDGj7MTm7pNU?utm_campaign=billboard",
      "position": {
        "Last Week": "42",
        "Peak Position": 15,
        "Wks on Chart": 30
      }
    }
  ]
}