{
  "name": "Rap",
  "chart_date": "2002-01-26",
  "tracks": [
    {
      "rank": 1,
      "title": "Round And Round",
      "artist": "Jonell & Method Man",
      "position": {
        "Last Week": "1",
        "Peak Position": 1,
        "Wks on Chart": 19
      }
    },
    {
      "rank": 2,
      "title": "That Was Then",
      "artist": "Roy Jones, Jr. Featuring Dave Hollister, Perion & Hahz The Rippa",
      "position": {
        "Last Week": "2",
        "Peak Position": 2,
        "Wks on Chart": 13
      }
    },
    {
      "rank": 3,
      "title": "Bunny Hop",
      "artist": "Da Entourage",
      "position": {
        "Last Week": "--",
        "Peak Position": 3,
        "Wks on Chart": 6
      }
    },
    {
      "rank": 4,
      "title": "Dansin Wit Wolvez",
      "artist": "Strik 9ine",
      "position": {
        "Last Week": "3",
        "Peak Position": 1,
        "Wks on Chart": 28
      }
    },
    {
      "rank": 5,
      "title": "Ain't Nobody (We Got It Locked!)",
      "artist": "The Rawlo Boys Featuring T.O.R.O. & Lil' Smoke",
      "position": {
        "Last Week": "8",
        "Peak Position": 4,
        "Wks on Chart": 15
      }
    },
    {
      "rank": 6,
      "title": "Think Big",
      "artist": "Crimewave",
      "position": {
        "Last Week": "4",
        "Peak Position": 4,
        "Wks on Chart": 29
      }
    },
    {
      "rank": 7,
      "title": "Jump Up In The Air",
      "artist": "Original P Introducing Hyped Up Westbound Soljaz",
      "position": {
        "Last Week": "6",
        "Peak Position": 2,
        "Wks on Chart": 28
      }
    },
    {
      "rank": 8,
      "title": "Buster",
      "artist": "Dennis Da Menace",
      "position": {
        "Last Week": "19",
        "Peak Position": 2,
        "Wks on Chart": 31
      }
    },
    {
      "rank": 9,
      "title": "Ground Zero (In Our Hearts You Will Remain)",
      "artist": "Cash & Computa",
      "position": {
        "Last Week": "5",
        "Peak Position": 2,
        "Wks on Chart": 12
      }
    },
    {
      "rank": 10,
      "title": "Got Ur Self A...",
      "artist": "Nas",
      "position": {
        "Last Week": "13",
        "Peak Position": 2,
        "Wks on Chart": 15
      }
    },
    {
      "rank": 11,
      "title": "2-Way",
      "artist": "Rayvon Featuring Shaggy, Ricardo \"Rik Rok\" Ducent, Brian & Tony Gold",
      "position": {
        "Last Week": "16",
        "Peak Position": 11,
        "Wks on Chart": 9
      }
    },
    {
      "rank": 12,
      "title": "Can I Get That?!!?",
      "artist": "Bear Witnez!",
      "position": {
        "Last Week": "7",
        "Peak Position": 3,
        "Wks on Chart": 22
      }
    },
    {
      "rank": 13,
      "title": "Playa Playa (Playing The Game Right)",
      "artist": "Minott Featuring Kurupted Seed",
      "position": {
        "Last Week": "10",
        "Peak Position": 8,
        "Wks on Chart": 12
      }
    },
    {
      "rank": 14,
      "title": "Always On Time",
      "artist": "Ja Rule Featuring Ashanti",
      "position": {
        "Last Week": "15",
        "Peak Position": 4,
        "Wks on Chart": 21
      }
    },
    {
      "rank": 15,
      "title": "Special Delivery",
      "artist": "G. Dep",
      "position": {
        "Last Week": "--",
        "Peak Position": 3,
        "Wks on Chart": 11
      }
    },
    {
      "rank": 16,
      "title": "Bouncin' Back (Bumpin' Me Against The Wall)",
      "artist": "Mystikal",
      "position": {
        "Last Week": "21",
        "Peak Position": 7,
        "Wks on Chart": 12
      }
    },
    {
      "rank": 17,
      "title": "Pimps/Players",
      "artist": "Skip Featuring Corey C",
      "position": {
        "Last Week": "20",
        "Peak Position": 8,
        "Wks on Chart": 6
      }
    },
    {
      "rank": 18,
      "title": "Young'n (Holla Back)",
      "artist": "Fabolous",
      "position": {
        "Last Week": "--",
        "Peak Position": 8,
        "Wks on Chart": 15
      }
    },
    {
      "rank": 19,
      "title": "We Thuggin'",
      "artist": "Fat Joe Featuring R. Kelly",
      "position": {
        "Last Week": "14",
        "Peak Position": 7,
        "Wks on Chart": 17
      }
    },
    {
      "rank": 20,
      "title": "Burn",
      "artist": "Mobb Deep Featuring Vita & Noyd",
      "position": {
        "Last Week": "25",
        "Peak Position": 14,
        "Wks on Chart": 9
      }
    },
    {
      "rank": 21,
      "title": "Uzi (Pinky Ring)",
      "artist": "Wu-Tang Clan",
      "position": {
        "Last Week": "--",
        "Peak Position": 16,
        "Wks on Chart": 2
      }
    },
    {
      "rank": 22,
      "title": "Fatty Girl",
      "artist": "Ludacris, LL Cool J & Keith Murray",
      "position": {
        "Last Week": "9",
        "Peak Position": 6,
        "Wks on Chart": 19
      }
    },
    {
      "rank": 23,
      "title": "Part II",
      "artist": "Method Man & Redman",
      "position": {
        "Last Week": "23",
        "Peak Position": 5,
        "Wks on Chart": 12
      }
    },
    {
      "rank": 24,
      "title": "Lights, Camera, Action!",
      "artist": "Mr. Cheeks",
      "position": {
        "Last Week": "17",
        "Peak Position": 1,
        "Wks on Chart": 27
      }
    },
    {
      "rank": 25,
      "title": "Gotta Have It",
      "artist": "Chocolate Bandit",
      "position": {
        "Last Week": "12",
        "Peak Position": 8,
        "Wks on Chart": 12
      }
    }
  ]
}