{
  "name": "Rap",
  "chart_date": "2001-11-17",
  "tracks": [
    {
      "rank": 1,
      "title": "Raise Up",
      "artist": "Petey Pablo",
      "cover": "http://www.billboard.com/images/pref_images/p57078olt04.jpg",
      "spotify": "http://open.spotify.com/track/02GwPAncasVL82yC7y2hmN?utm_campaign=billboard",
      "position": {
        "Last Week": "1",
        "Peak Position": 1,
        "Wks on Chart": 19
      }
    },
    {
      "rank": 2,
      "title": "Nothing's Wrong",
      "artist": "Won-G Featuring DJ Quik",
      "spotify": "http://open.spotify.com/track/0Tx6SFqPBUlxWw1wTDbJQF?utm_campaign=billboard",
      "position": {
        "Last Week": "3",
        "Peak Position": 2,
        "Wks on Chart": 9
      }
    },
    {
      "rank": 3,
      "title": "Ground Zero (In Our Hearts You Will Remain)",
      "artist": "Cash & Computa",
      "position": {
        "Last Week": "--",
        "Peak Position": 2,
        "Wks on Chart": 12
      }
    },
    {
      "rank": 4,
      "title": "I'm Your Girl",
      "artist": "Dena Cali",
      "position": {
        "Last Week": "2",
        "Peak Position": 2,
        "Wks on Chart": 12
      }
    },
    {
      "rank": 5,
      "title": "Jump Up In The Air",
      "artist": "Original P Introducing Hyped Up Westbound Soljaz",
      "position": {
        "Last Week": "6",
        "Peak Position": 2,
        "Wks on Chart": 28
      }
    },
    {
      "rank": 6,
      "title": "The Bedrock",
      "artist": "Phatty Banks Presents Club Drama",
      "position": {
        "Last Week": "22",
        "Peak Position": 6,
        "Wks on Chart": 6
      }
    },
    {
      "rank": 7,
      "title": "Buster",
      "artist": "Dennis Da Menace",
      "position": {
        "Last Week": "5",
        "Peak Position": 2,
        "Wks on Chart": 31
      }
    },
    {
      "rank": 8,
      "title": "Playa Playa (Playing The Game Right)",
      "artist": "Minott Featuring Kurupted Seed",
      "position": {
        "Last Week": "--",
        "Peak Position": 8,
        "Wks on Chart": 12
      }
    },
    {
      "rank": 9,
      "title": "Gotta Have It",
      "artist": "Chocolate Bandit",
      "position": {
        "Last Week": "10",
        "Peak Position": 8,
        "Wks on Chart": 12
      }
    },
    {
      "rank": 10,
      "title": "Think Big",
      "artist": "Crimewave",
      "position": {
        "Last Week": "12",
        "Peak Position": 4,
        "Wks on Chart": 29
      }
    },
    {
      "rank": 11,
      "title": "Po' Punch",
      "artist": "Po' White Trash And The Trailer Park Symphony",
      "position": {
        "Last Week": "9",
        "Peak Position": 3,
        "Wks on Chart": 19
      }
    },
    {
      "rank": 12,
      "title": "Dansin Wit Wolvez",
      "artist": "Strik 9ine",
      "position": {
        "Last Week": "--",
        "Peak Position": 1,
        "Wks on Chart": 28
      }
    },
    {
      "rank": 13,
      "title": "Always On Time",
      "artist": "Ja Rule Featuring Ashanti",
      "cover": "http://www.billboard.com/images/pref_images/p56481wjlv7.jpg",
      "spotify": "http://open.spotify.com/track/4YA7nxDtAVE2R1Eryx7uRu?utm_campaign=billboard",
      "position": {
        "Last Week": "--",
        "Peak Position": 4,
        "Wks on Chart": 21
      }
    },
    {
      "rank": 14,
      "title": "Do U Wanna Roll (Dolittle Theme)",
      "artist": "R.L., Snoop Dogg & Lil' Kim",
      "position": {
        "Last Week": "--",
        "Peak Position": 11,
        "Wks on Chart": 7
      }
    },
    {
      "rank": 15,
      "title": "Bounce",
      "artist": "Survivalist",
      "position": {
        "Last Week": "19",
        "Peak Position": 5,
        "Wks on Chart": 11
      }
    },
    {
      "rank": 16,
      "title": "We Thuggin'",
      "artist": "Fat Joe Featuring R. Kelly",
      "cover": "http://www.billboard.com/images/pref_images/p68299ddp0v.jpg",
      "spotify": "http://open.spotify.com/track/2EcW94ak7kYH4mDMvI7iWg?utm_campaign=billboard",
      "position": {
        "Last Week": "14",
        "Peak Position": 7,
        "Wks on Chart": 17
      }
    },
    {
      "rank": 17,
      "title": "Let's Be Friends",
      "artist": "TaTa + Brando Featuring Larry Poteat Of The Donz",
      "position": {
        "Last Week": "11",
        "Peak Position": 5,
        "Wks on Chart": 17
      }
    },
    {
      "rank": 18,
      "title": "My Life",
      "artist": "Kool G Rap Featuring G Wise",
      "cover": "http://www.billboard.com/images/pref_images/p74966jx3d5.jpg",
      "spotify": "http://open.spotify.com/track/75g02AdkzWr8Ly8GL10utr?utm_campaign=billboard",
      "position": {
        "Last Week": "8",
        "Peak Position": 6,
        "Wks on Chart": 6
      }
    },
    {
      "rank": 19,
      "title": "How We Do",
      "artist": "Big Lew BKA Popeye Reds Featuring Nonchalant",
      "position": {
        "Last Week": "7",
        "Peak Position": 2,
        "Wks on Chart": 8
      }
    },
    {
      "rank": 20,
      "title": "Make It Vibrate",
      "artist": "Rising Son",
      "position": {
        "Last Week": "13",
        "Peak Position": 9,
        "Wks on Chart": 17
      }
    },
    {
      "rank": 21,
      "title": "Ugly",
      "artist": "Bubba Sparxxx",
      "cover": "http://www.billboard.com/images/pref_images/q06143j0q80.jpg",
      "spotify": "http://open.spotify.com/track/3NOq1Gpiy4KwDni8NhOmHQ?utm_campaign=billboard",
      "position": {
        "Last Week": "17",
        "Peak Position": 6,
        "Wks on Chart": 11
      }
    },
    {
      "rank": 22,
      "title": "Burn",
      "artist": "Mobb Deep Featuring Vita & Noyd",
      "cover": "http://www.billboard.com/images/pref_images/q18067n78u1.jpg",
      "spotify": "http://open.spotify.com/track/20ccLIFUpfzgX5kSbDakH4?utm_campaign=billboard",
      "position": {
        "Last Week": "--",
        "Peak Position": 14,
        "Wks on Chart": 9
      }
    },
    {
      "rank": 23,
      "title": "Break Ya Neck",
      "artist": "Busta Rhymes",
      "cover": "http://www.billboard.com/images/pref_images/p70920kv04c.jpg",
      "spotify": "http://open.spotify.com/track/0svl7cK07gK1ia5ainczU5?utm_campaign=billboard",
      "position": {
        "Last Week": "15",
        "Peak Position": 9,
        "Wks on Chart": 17
      }
    },
    {
      "rank": 24,
      "title": "Cut Throat",
      "artist": "John Got'ti",
      "position": {
        "Last Week": "--",
        "Peak Position": 12,
        "Wks on Chart": 11
      }
    },
    {
      "rank": 25,
      "title": "2-Way",
      "artist": "Rayvon Featuring Shaggy, Ricardo \"Rik Rok\" Ducent, Brian & Tony Gold",
      "spotify": "http://open.spotify.com/track/2RBcXONSdZ02Vh14pTs00r?utm_campaign=billboard",
      "position": {
        "Last Week": "25",
        "Peak Position": 11,
        "Wks on Chart": 9
      }
    }
  ]
}