{
  "name": "Club",
  "chart_date": "1984-01-28",
  "tracks": [
    {
      "rank": 1,
      "title": "Trommeltanz (din Daa Daa)",
      "artist": "George Kranz",
      "position": {
        "Last Week": "1",
        "Peak Position": 1,
        "Wks on Chart": 19
      }
    },
    {
      "rank": 2,
      "title": "I Need You / Automatic",
      "artist": "The Pointer Sisters",
      "position": {
        "Last Week": "2",
        "Peak Position": 2,
        "Wks on Chart": 24
      }
    },
    {
      "rank": 3,
      "title": "WHITE HORSE",
      "artist": "Laid Back",
      "position": {
        "Last Week": "6",
        "Peak Position": 1,
        "Wks on Chart": 18
      }
    },
    {
      "rank": 4,
      "title": "OVER MY HEAD",
      "artist": "Toni Basil",
      "position": {
        "Last Week": "5",
        "Peak Position": 4,
        "Wks on Chart": 16
      }
    },
    {
      "rank": 5,
      "title": "Owner Of A Lonely Heart",
      "artist": "Yes",
      "position": {
        "Last Week": "3",
        "Peak Position": 3,
        "Wks on Chart": 14
      }
    },
    {
      "rank": 6,
      "title": "BEAT BOX",
      "artist": "The Art Of Noise",
      "position": {
        "Last Week": "13",
        "Peak Position": 1,
        "Wks on Chart": 16
      }
    },
    {
      "rank": 7,
      "title": "ON THE UPSIDE",
      "artist": "Xena",
      "position": {
        "Last Week": "8",
        "Peak Position": 7,
        "Wks on Chart": 17
      }
    },
    {
      "rank": 8,
      "title": "THE POLITICS OF DANCING",
      "artist": "Re-flex",
      "position": {
        "Last Week": "10",
        "Peak Position": 8,
        "Wks on Chart": 15
      }
    },
    {
      "rank": 9,
      "title": "TOUR DE FRANCE",
      "artist": "Kraftwerk",
      "position": {
        "Last Week": "22",
        "Peak Position": 4,
        "Wks on Chart": 25
      }
    },
    {
      "rank": 10,
      "title": "Remember What You Like",
      "artist": "Jenny Burton",
      "position": {
        "Last Week": "11",
        "Peak Position": 10,
        "Wks on Chart": 16
      }
    },
    {
      "rank": 11,
      "title": "Colour By Numbers (all cuts)",
      "artist": "Culture Club",
      "position": {
        "Last Week": "7",
        "Peak Position": 3,
        "Wks on Chart": 16
      }
    },
    {
      "rank": 12,
      "title": "NEW SONG",
      "artist": "Howard Jones",
      "position": {
        "Last Week": "20",
        "Peak Position": 4,
        "Wks on Chart": 15
      }
    },
    {
      "rank": 13,
      "title": "PUMPING VELVET/NO MORE WORDS",
      "artist": "Yello",
      "position": {
        "Last Week": "14",
        "Peak Position": 12,
        "Wks on Chart": 12
      }
    },
    {
      "rank": 14,
      "title": "Where Is My Man",
      "artist": "Eartha Kitt",
      "position": {
        "Last Week": "9",
        "Peak Position": 7,
        "Wks on Chart": 14
      }
    },
    {
      "rank": 15,
      "title": "CRAZY CUTS",
      "artist": "Grandmixer D.St.",
      "position": {
        "Last Week": "24",
        "Peak Position": 15,
        "Wks on Chart": 9
      }
    },
    {
      "rank": 16,
      "title": "TOO LATE/TROUBLE IN PARADISE",
      "artist": "Sylvester",
      "position": {
        "Last Week": "16",
        "Peak Position": 16,
        "Wks on Chart": 16
      }
    },
    {
      "rank": 17,
      "title": "B-BOYS BEWARE/DESTINY",
      "artist": "Two Sisters",
      "position": {
        "Last Week": "17",
        "Peak Position": 16,
        "Wks on Chart": 14
      }
    },
    {
      "rank": 18,
      "title": "Action",
      "artist": "Evelyn \"Champagne\" King",
      "position": {
        "Last Week": "26",
        "Peak Position": 13,
        "Wks on Chart": 12
      }
    },
    {
      "rank": 19,
      "title": "Say It Isn't So",
      "artist": "Daryl Hall John Oates",
      "position": {
        "Last Week": "4",
        "Peak Position": 1,
        "Wks on Chart": 11
      }
    },
    {
      "rank": 20,
      "title": "UNDERCOVER OF THE NIGHT",
      "artist": "The Rolling Stones",
      "position": {
        "Last Week": "15",
        "Peak Position": 9,
        "Wks on Chart": 12
      }
    },
    {
      "rank": 21,
      "title": "ENCORE",
      "artist": "Cheryl Lynn",
      "position": {
        "Last Week": "38",
        "Peak Position": 6,
        "Wks on Chart": 17
      }
    },
    {
      "rank": 22,
      "title": "PREPARE TO ENERGIZE",
      "artist": "Torch Song",
      "position": {
        "Last Week": "29",
        "Peak Position": 8,
        "Wks on Chart": 12
      }
    },
    {
      "rank": 23,
      "title": "BAD TIMES (I CAN't STAND IT)",
      "artist": "Captain Rapp",
      "position": {
        "Last Week": "25",
        "Peak Position": 23,
        "Wks on Chart": 16
      }
    },
    {
      "rank": 24,
      "title": "Share The Night",
      "artist": "World Premiere",
      "position": {
        "Last Week": "42",
        "Peak Position": 15,
        "Wks on Chart": 9
      }
    },
    {
      "rank": 25,
      "title": "ROCK IT TO YOUR HEART/MANDATORY LOVE",
      "artist": "Lisa",
      "position": {
        "Last Week": "12",
        "Peak Position": 2,
        "Wks on Chart": 15
      }
    },
    {
      "rank": 26,
      "title": "EARTHQUAKE",
      "artist": "Flirtations",
      "position": {
        "Last Week": "27",
        "Peak Position": 26,
        "Wks on Chart": 11
      }
    },
    {
      "rank": 27,
      "title": "NUMBER ONE",
      "artist": "Aida",
      "position": {
        "Last Week": "46",
        "Peak Position": 19,
        "Wks on Chart": 9
      }
    },
    {
      "rank": 28,
      "title": "RUSH RUSH",
      "artist": "Debbie Harry",
      "position": {
        "Last Week": "39",
        "Peak Position": 28,
        "Wks on Chart": 12
      }
    },
    {
      "rank": 29,
      "title": "SHOO-SHOO-WAH",
      "artist": "The World",
      "position": {
        "Last Week": "30",
        "Peak Position": 26,
        "Wks on Chart": 8
      }
    },
    {
      "rank": 30,
      "title": "WATCH THE CLOSING DOORS",
      "artist": "I.R.T.",
      "position": {
        "Last Week": "64",
        "Peak Position": 6,
        "Wks on Chart": 15
      }
    },
    {
      "rank": 31,
      "title": "Twenty Questions",
      "artist": "Tictoc",
      "position": {
        "Last Week": "48",
        "Peak Position": 31,
        "Wks on Chart": 7
      }
    },
    {
      "rank": 32,
      "title": "RITESPOT",
      "artist": "Blue Print",
      "position": {
        "Last Week": "32",
        "Peak Position": 32,
        "Wks on Chart": 10
      }
    },
    {
      "rank": 33,
      "title": "LIAR ON THE WIRE",
      "artist": "Sharon Redd",
      "position": {
        "Last Week": "34",
        "Peak Position": 33,
        "Wks on Chart": 9
      }
    },
    {
      "rank": 34,
      "title": "Relax",
      "artist": "Frankie Goes To Hollywood",
      "position": {
        "Last Week": "51",
        "Peak Position": 20,
        "Wks on Chart": 13
      }
    },
    {
      "rank": 35,
      "title": "TALKING IN YOUR SLEEP",
      "artist": "The Romantics",
      "position": {
        "Last Week": "21",
        "Peak Position": 1,
        "Wks on Chart": 15
      }
    },
    {
      "rank": 36,
      "title": "Autodrive",
      "artist": "Herbie Hancock",
      "position": {
        "Last Week": "37",
        "Peak Position": 36,
        "Wks on Chart": 12
      }
    },
    {
      "rank": 37,
      "title": "NEED SOMEBODY NEW",
      "artist": "The Jamaica Girls",
      "position": {
        "Last Week": "23",
        "Peak Position": 23,
        "Wks on Chart": 11
      }
    },
    {
      "rank": 38,
      "title": "THE WAY OF LIFE",
      "artist": "The Puppets",
      "position": {
        "Last Week": "58",
        "Peak Position": 6,
        "Wks on Chart": 12
      }
    },
    {
      "rank": 39,
      "title": "The Record Keeps Spinning",
      "artist": "Indeep",
      "position": {
        "Last Week": "60",
        "Peak Position": 32,
        "Wks on Chart": 9
      }
    },
    {
      "rank": 40,
      "title": "UNION OF THE SNAKE",
      "artist": "Duran Duran",
      "position": {
        "Last Week": "33",
        "Peak Position": 33,
        "Wks on Chart": 8
      }
    },
    {
      "rank": 41,
      "title": "Love Is A Battlefield",
      "artist": "Pat Benatar",
      "position": {
        "Last Week": "41",
        "Peak Position": 41,
        "Wks on Chart": 9
      }
    },
    {
      "rank": 42,
      "title": "(I'm JUST A) SUCKER FOR A PRETTY FACE",
      "artist": "West Phillips",
      "position": {
        "Last Week": "53",
        "Peak Position": 25,
        "Wks on Chart": 13
      }
    },
    {
      "rank": 43,
      "title": "New York New York",
      "artist": "Nina Hagen",
      "position": {
        "Last Week": "59",
        "Peak Position": 9,
        "Wks on Chart": 13
      }
    },
    {
      "rank": 44,
      "title": "IS IT LOVE",
      "artist": "Gang Of Four",
      "position": {
        "Last Week": "18",
        "Peak Position": 8,
        "Wks on Chart": 15
      }
    },
    {
      "rank": 45,
      "title": "LET THE MUSIC PLAY",
      "artist": "Shannon",
      "position": {
        "Last Week": "35",
        "Peak Position": 1,
        "Wks on Chart": 19
      }
    },
    {
      "rank": 46,
      "title": "Life Is The Reason / Maybe This Time",
      "artist": "Norma",
      "position": {
        "Last Week": "56",
        "Peak Position": 46,
        "Wks on Chart": 9
      }
    },
    {
      "rank": 47,
      "title": "LOVE CARES",
      "artist": "Endgames",
      "position": {
        "Last Week": "55",
        "Peak Position": 47,
        "Wks on Chart": 8
      }
    },
    {
      "rank": 48,
      "title": "The Dream <P6>(Hold On To Your Dream)",
      "artist": "Irene Cara",
      "position": {
        "Last Week": "--",
        "Peak Position": 26,
        "Wks on Chart": 8
      }
    },
    {
      "rank": 49,
      "title": "POP GOES MY LOVE/SCRATCH GOES MY DUB",
      "artist": "Freeez",
      "position": {
        "Last Week": "19",
        "Peak Position": 5,
        "Wks on Chart": 14
      }
    },
    {
      "rank": 50,
      "title": "REBEL YELL",
      "artist": "Billy Idol",
      "position": {
        "Last Week": "54",
        "Peak Position": 50,
        "Wks on Chart": 9
      }
    }
  ]
}