{
  "name": "Club",
  "chart_date": "2000-01-08",
  "tracks": [
    {
      "rank": 1,
      "title": "Fly Away (Bye Bye)",
      "artist": "Eyes Cream",
      "position": {
        "Last Week": "2",
        "Peak Position": 1,
        "Wks on Chart": 13
      }
    },
    {
      "rank": 2,
      "title": "Supersonic",
      "artist": "Jamiroquai",
      "position": {
        "Last Week": "4",
        "Peak Position": 1,
        "Wks on Chart": 14
      }
    },
    {
      "rank": 3,
      "title": "Ain t That A Lot Of Love",
      "artist": "Simply Red",
      "position": {
        "Last Week": "3",
        "Peak Position": 3,
        "Wks on Chart": 14
      }
    },
    {
      "rank": 4,
      "title": "All Around The World",
      "artist": "Soul Solution Featuring Carolyn Harding",
      "position": {
        "Last Week": "5",
        "Peak Position": 4,
        "Wks on Chart": 14
      }
    },
    {
      "rank": 5,
      "title": "17 Again",
      "artist": "Eurythmics",
      "position": {
        "Last Week": "1",
        "Peak Position": 1,
        "Wks on Chart": 11
      }
    },
    {
      "rank": 6,
      "title": "Above The Clouds",
      "artist": "Amber",
      "position": {
        "Last Week": "8",
        "Peak Position": 1,
        "Wks on Chart": 13
      }
    },
    {
      "rank": 7,
      "title": "That Sound",
      "artist": "Michael Moog",
      "position": {
        "Last Week": "10",
        "Peak Position": 1,
        "Wks on Chart": 15
      }
    },
    {
      "rank": 8,
      "title": "Dov e L Amore",
      "artist": "Cher",
      "position": {
        "Last Week": "11",
        "Peak Position": 5,
        "Wks on Chart": 13
      }
    },
    {
      "rank": 9,
      "title": "Take Me Love Me (Squeeze Me Baby)",
      "artist": "Friburn",
      "position": {
        "Last Week": "15",
        "Peak Position": 4,
        "Wks on Chart": 15
      }
    },
    {
      "rank": 10,
      "title": "Wake Up",
      "artist": "Dawn Tallman",
      "position": {
        "Last Week": "17",
        "Peak Position": 10,
        "Wks on Chart": 12
      }
    },
    {
      "rank": 11,
      "title": "Mysterious Times",
      "artist": "Sash! Featuring Tina Cousins",
      "position": {
        "Last Week": "12",
        "Peak Position": 11,
        "Wks on Chart": 13
      }
    },
    {
      "rank": 12,
      "title": "Do It Properly",
      "artist": "The Collaboration (Victor Calderone",
      "position": {
        "Last Week": "7",
        "Peak Position": 9,
        "Wks on Chart": 14
      }
    },
    {
      "rank": 13,
      "title": "Get Get Down",
      "artist": "Paul Johnson",
      "position": {
        "Last Week": "6",
        "Peak Position": 1,
        "Wks on Chart": 18
      }
    },
    {
      "rank": 14,
      "title": "Take A Picture",
      "artist": "Filter",
      "position": {
        "Last Week": "22",
        "Peak Position": 1,
        "Wks on Chart": 13
      }
    },
    {
      "rank": 15,
      "title": "It s A Fine Day",
      "artist": "Miss Jane",
      "position": {
        "Last Week": "9",
        "Peak Position": 4,
        "Wks on Chart": 14
      }
    },
    {
      "rank": 16,
      "title": "Don t Go (1999 Mixes)",
      "artist": "Yaz",
      "position": {
        "Last Week": "19",
        "Peak Position": 16,
        "Wks on Chart": 11
      }
    },
    {
      "rank": 17,
      "title": "Get Down",
      "artist": "Avant Garde",
      "position": {
        "Last Week": "13",
        "Peak Position": 12,
        "Wks on Chart": 13
      }
    },
    {
      "rank": 18,
      "title": "Rendez-Vu",
      "artist": "Basement Jaxx",
      "position": {
        "Last Week": "14",
        "Peak Position": 1,
        "Wks on Chart": 14
      }
    },
    {
      "rank": 19,
      "title": "Don t Stop",
      "artist": "Freestylers",
      "position": {
        "Last Week": "26",
        "Peak Position": 8,
        "Wks on Chart": 14
      }
    },
    {
      "rank": 20,
      "title": "Void (I Need You)",
      "artist": "Catapila",
      "position": {
        "Last Week": "23",
        "Peak Position": 10,
        "Wks on Chart": 14
      }
    },
    {
      "rank": 21,
      "title": "Never Dance",
      "artist": "Linda Eder",
      "position": {
        "Last Week": "25",
        "Peak Position": 17,
        "Wks on Chart": 11
      }
    },
    {
      "rank": 22,
      "title": "I Rock",
      "artist": "Tom Novy Featuring Virginia",
      "position": {
        "Last Week": "21",
        "Peak Position": 21,
        "Wks on Chart": 11
      }
    },
    {
      "rank": 23,
      "title": "I m Outta Love",
      "artist": "Anastacia",
      "position": {
        "Last Week": "30",
        "Peak Position": 2,
        "Wks on Chart": 15
      }
    },
    {
      "rank": 24,
      "title": "Rhythm Divine",
      "artist": "Enrique Iglesias",
      "position": {
        "Last Week": "27",
        "Peak Position": 4,
        "Wks on Chart": 14
      }
    },
    {
      "rank": 25,
      "title": "New York City Boy",
      "artist": "Pet Shop Boys",
      "position": {
        "Last Week": "16",
        "Peak Position": 1,
        "Wks on Chart": 14
      }
    },
    {
      "rank": 26,
      "title": "Listen To The People",
      "artist": "Small Voices Calling Featuring Martha Wash",
      "position": {
        "Last Week": "31",
        "Peak Position": 14,
        "Wks on Chart": 14
      }
    },
    {
      "rank": 27,
      "title": "(Just) Me And You",
      "artist": "New Vision",
      "position": {
        "Last Week": "18",
        "Peak Position": 5,
        "Wks on Chart": 15
      }
    },
    {
      "rank": 28,
      "title": "Blue (Da Ba Dee)",
      "artist": "Eiffel 65",
      "position": {
        "Last Week": "40",
        "Peak Position": 6,
        "Wks on Chart": 13
      }
    },
    {
      "rank": 29,
      "title": "(I) Get Lost",
      "artist": "Eric Clapton",
      "position": {
        "Last Week": "36",
        "Peak Position": 8,
        "Wks on Chart": 13
      }
    },
    {
      "rank": 30,
      "title": "La Mouche",
      "artist": "Cassius",
      "position": {
        "Last Week": "32",
        "Peak Position": 27,
        "Wks on Chart": 10
      }
    },
    {
      "rank": 31,
      "title": "Encore (Ooh Ooh Yeah Yeah)",
      "artist": "Sugarbabies",
      "position": {
        "Last Week": "20",
        "Peak Position": 6,
        "Wks on Chart": 13
      }
    },
    {
      "rank": 32,
      "title": "Man=Drug",
      "artist": "Lula",
      "position": {
        "Last Week": "24",
        "Peak Position": 6,
        "Wks on Chart": 12
      }
    },
    {
      "rank": 33,
      "title": "He Loves Me 2",
      "artist": "CeCe Peniston",
      "position": {
        "Last Week": "35",
        "Peak Position": 24,
        "Wks on Chart": 15
      }
    },
    {
      "rank": 34,
      "title": "Al-Naafyish (The Soul)-Y2K Mixes",
      "artist": "Hashim",
      "position": {
        "Last Week": "45",
        "Peak Position": 11,
        "Wks on Chart": 13
      }
    },
    {
      "rank": 35,
      "title": "Horny Horns",
      "artist": "Perfect Phase",
      "position": {
        "Last Week": "50",
        "Peak Position": 4,
        "Wks on Chart": 14
      }
    },
    {
      "rank": 36,
      "title": "Deep In U",
      "artist": "Al E Mood",
      "position": {
        "Last Week": "43",
        "Peak Position": 28,
        "Wks on Chart": 10
      }
    },
    {
      "rank": 37,
      "title": "Temperamental",
      "artist": "Everything But The Girl",
      "position": {
        "Last Week": "54",
        "Peak Position": 1,
        "Wks on Chart": 11
      }
    },
    {
      "rank": 38,
      "title": "Move Your Body",
      "artist": "Osio",
      "position": {
        "Last Week": "47",
        "Peak Position": 24,
        "Wks on Chart": 10
      }
    },
    {
      "rank": 39,
      "title": "Gotta Have Love",
      "artist": "Plasmic Honey",
      "position": {
        "Last Week": "34",
        "Peak Position": 8,
        "Wks on Chart": 14
      }
    },
    {
      "rank": 40,
      "title": "Everything Will Flow",
      "artist": "The London Suede",
      "position": {
        "Last Week": "33",
        "Peak Position": 28,
        "Wks on Chart": 11
      }
    },
    {
      "rank": 41,
      "title": "Sun Is Shining",
      "artist": "Bob Marley Vs. Funkstar De Luxe",
      "position": {
        "Last Week": "28",
        "Peak Position": 1,
        "Wks on Chart": 15
      }
    },
    {
      "rank": 42,
      "title": "Tuva Groove",
      "artist": "Ondar",
      "position": {
        "Last Week": "29",
        "Peak Position": 14,
        "Wks on Chart": 11
      }
    },
    {
      "rank": 43,
      "title": "I See You Baby",
      "artist": "Groove Armada",
      "position": {
        "Last Week": "--",
        "Peak Position": 12,
        "Wks on Chart": 13
      }
    },
    {
      "rank": 44,
      "title": "The Temple",
      "artist": "Erin Hamilton",
      "position": {
        "Last Week": "49",
        "Peak Position": 42,
        "Wks on Chart": 5
      }
    },
    {
      "rank": 45,
      "title": "Soulshaka",
      "artist": "Jan Driver",
      "position": {
        "Last Week": "--",
        "Peak Position": 44,
        "Wks on Chart": 3
      }
    },
    {
      "rank": 46,
      "title": "Takin Me Higher",
      "artist": "Deepswing Featuring Xavior",
      "position": {
        "Last Week": "37",
        "Peak Position": 26,
        "Wks on Chart": 10
      }
    },
    {
      "rank": 47,
      "title": "Something...(For The DJ s)",
      "artist": "Chris Cox",
      "position": {
        "Last Week": "42",
        "Peak Position": 31,
        "Wks on Chart": 10
      }
    },
    {
      "rank": 48,
      "title": "I Believe In Love",
      "artist": "Paula Cole Band",
      "position": {
        "Last Week": "--",
        "Peak Position": 18,
        "Wks on Chart": 12
      }
    },
    {
      "rank": 49,
      "title": "Groove With Me Tonight",
      "artist": "MDO",
      "position": {
        "Last Week": "44",
        "Peak Position": 33,
        "Wks on Chart": 8
      }
    },
    {
      "rank": 50,
      "title": "Can t Help It",
      "artist": "Funky Green Dogs",
      "position": {
        "Last Week": "--",
        "Peak Position": 33,
        "Wks on Chart": 8
      }
    }
  ]
}